rum_with_telegram/__init__.py
rum_with_telegram/config.py
rum_with_telegram/data_exchanger.py
rum_with_telegram/db_handle.py
rum_with_telegram/module.py
rum_with_telegram-1.0.4.dist-info/LICENSE
rum_with_telegram-1.0.4.dist-info/METADATA
rum_with_telegram-1.0.4.dist-info/WHEEL
rum_with_telegram-1.0.4.dist-info/top_level.txt
rum_with_telegram-1.0.4.dist-info/RECORD
