Metadata-Version: 2.1
Name: rum-with-telegram
Version: 1.0.4
Summary: A bot, send telegram update to rum group as trx, and get new trx from rum group to channel.
Home-page: https://github.com/liujuanjuan1984/rum_with_telegram
Author: liujuanjuan1984
Author-email: qiaoanlu@163.com
Project-URL: Github Repo, https://github.com/liujuanjuan1984/rum_with_telegram
Project-URL: Bug Tracker, https://github.com/liujuanjuan1984/rum_with_telegram/issues
Project-URL: About Quorum, https://github.com/rumsystem/quorum
Keywords: python-telegram-bot,rumsystem,quorum
Classifier: Programming Language :: Python :: 3
Classifier: Programming Language :: Python :: 3.7
Classifier: Programming Language :: Python :: 3.8
Classifier: Programming Language :: Python :: 3.9
Classifier: Programming Language :: Python :: 3.10
Classifier: License :: OSI Approved :: MIT License
Classifier: Operating System :: OS Independent
Requires-Python: >=3.7
License-File: LICENSE
Requires-Dist: python-telegram-bot (==20.2)
Requires-Dist: quorum-data-py (>=1.2.7)
Requires-Dist: quorum-mininode-py
Requires-Dist: sqlalchemy
